pyweather/__init__.py
pyweather/airpol.py
pyweather/apmodel.py
pyweather/constants.py
pyweather/curweath.py
pyweather/cwmodel.py
py_open_weather-0.1.3.dist-info/LICENSE.txt
py_open_weather-0.1.3.dist-info/METADATA
py_open_weather-0.1.3.dist-info/WHEEL
py_open_weather-0.1.3.dist-info/top_level.txt
py_open_weather-0.1.3.dist-info/RECORD
