Metadata-Version: 2.1
Name: py-open-weather
Version: 0.1.3
Summary: A python3 library providing information of Current & Forecast of Weather as well as Air Pollution based on data from OpenWeatherMap.
Home-page: https://github.com/ravigoel08/py-open-weather
Author: CodewithRv
Author-email: ravigoel.1997@gmail.com
License: MIT
Keywords: open weather api,owm,weather,weather api,pyweather,open weather,air pollution,py-open-weather
Platform: UNKNOWN
Classifier: Intended Audience :: Developers
Classifier: Topic :: Software Development :: Build Tools
Classifier: License :: OSI Approved :: MIT License
Classifier: Programming Language :: Python :: 3
Classifier: Programming Language :: Python :: 3.4
Classifier: Programming Language :: Python :: 3.5
Classifier: Programming Language :: Python :: 3.6
Classifier: Programming Language :: Python :: 3.9
Classifier: Operating System :: OS Independent
Requires-Dist: requests
Requires-Dist: pydantic
Requires-Dist: orjson
